sphinx_doc/__init__.py
sphinx_doc/autodoc.py
sphinx_doc/py.typed
python_sphinx_doc-0.1.dist-info/LICENSE
python_sphinx_doc-0.1.dist-info/METADATA
python_sphinx_doc-0.1.dist-info/WHEEL
python_sphinx_doc-0.1.dist-info/top_level.txt
python_sphinx_doc-0.1.dist-info/zip-safe
python_sphinx_doc-0.1.dist-info/RECORD
