Metadata-Version: 2.1
Name: python-sphinx-doc
Version: 0.1
Summary: Enrich Sphinx documentation with Python type information
Author: Levente Hunyadi
Author-email: hunyadi@gmail.com
License: MIT
Classifier: Development Status :: 5 - Production/Stable
Classifier: Environment :: Console
Classifier: Intended Audience :: Developers
Classifier: Intended Audience :: End Users/Desktop
Classifier: License :: OSI Approved :: MIT License
Classifier: Operating System :: OS Independent
Classifier: Programming Language :: Python :: 3
Classifier: Programming Language :: Python :: 3.9
Classifier: Programming Language :: Python :: 3.10
Classifier: Programming Language :: Python :: 3.11
Classifier: Programming Language :: Python :: 3.12
Classifier: Topic :: Documentation :: Sphinx
Classifier: Typing :: Typed
Requires-Python: >=3.9
License-File: LICENSE
Requires-Dist: json_strong_typing
Requires-Dist: pysqlsync
Requires-Dist: sphinx
Requires-Dist: sphinx-design
